<?xml version="1.0" encoding="utf-8"?>
<!DOCTYPE hibernate-mapping PUBLIC "-//Hibernate/Hibernate Mapping DTD 3.0//EN"
"http://hibernate.sourceforge.net/hibernate-mapping-3.0.dtd">
<!-- 
    Mapping file autogenerated by MyEclipse Persistence Tools
-->
<hibernate-mapping>
    <class name="com.qcmz.cmc.entity.CmcCtBlacklist" table="CMC_CT_BLACKLIST" catalog="cmc">
        <id name="userid" type="java.lang.Long">
            <column name="USERID" />
            <generator class="assigned" />
        </id>        
        <property name="reason" type="java.lang.String">
            <column name="REASON" length="100">
                <comment>原因</comment>
            </column>
        </property>
        <property name="createtime" type="java.util.Date">
            <column name="CREATETIME" length="19" not-null="true">
                <comment>创建时间</comment>
            </column>
        </property>
    </class>
</hibernate-mapping>
