<?xml version="1.0" encoding="utf-8"?>
<!DOCTYPE hibernate-mapping PUBLIC "-//Hibernate/Hibernate Mapping DTD 3.0//EN"
"http://hibernate.sourceforge.net/hibernate-mapping-3.0.dtd">
<!-- 
    Mapping file autogenerated by MyEclipse Persistence Tools
-->
<hibernate-mapping>
    <class name="com.qcmz.cmc.entity.CmcRDub" table="CMC_R_DUB" catalog="cmc">
        <id name="id" type="java.lang.Long">
            <column name="ID" />
            <generator class="identity" />
        </id>
        <property name="orderid" type="java.lang.String">
            <column name="ORDERID" length="20" not-null="true">
                <comment>订单编号</comment>
            </column>
        </property>
        <many-to-one name="cmcROrder" class="com.qcmz.cmc.entity.CmcROrder" fetch="select" insert="false" update="false">
            <column name="ORDERID" length="20" not-null="true">
                <comment>订单编号</comment>
            </column>
        </many-to-one>
        <property name="userid" type="java.lang.Long">
            <column name="USERID" not-null="true">
                <comment>用户编号</comment>
            </column>
        </property>
        <property name="title" type="java.lang.String">
            <column name="TITLE" length="100">
                <comment>名称</comment>
            </column>
        </property>
        <property name="txt" type="java.lang.String">
            <column name="TXT" length="65535" not-null="true">
                <comment>文本</comment>
            </column>
        </property>
        <property name="dubberid" type="java.lang.Long">
            <column name="DUBBERID">
                <comment>配音员编号</comment>
            </column>
        </property>
        <many-to-one name="cmcDubber" class="com.qcmz.cmc.entity.CmcDubber" fetch="select" not-found="ignore" insert="false" update="false">
            <column name="DUBBERID">
                <comment>配音员编号</comment>
            </column>
        </many-to-one>
        <property name="audio" type="java.lang.String">
            <column name="AUDIO" length="200">
                <comment>音频</comment>
            </column>
        </property>
    </class>
</hibernate-mapping>
